concentrationMetrics/__init__.py
concentrationMetrics/model.py
datasets/__init__.py
examples/python/BCI_example.py
examples/python/__init__.py
examples/python/atkinson_example.py
examples/python/confidence_interval_example.py
examples/python/ellison_glaeser_example.py
examples/python/error_checking.py
examples/python/gini_example.py
examples/python/graph_example.py
examples/python/interface_examples.py
examples/python/semantic_documentation.py
examples/python/simulation_plots.py
concentrationMetrics-0.6.0.dist-info/LICENSE.txt
concentrationMetrics-0.6.0.dist-info/METADATA
concentrationMetrics-0.6.0.dist-info/WHEEL
concentrationMetrics-0.6.0.dist-info/top_level.txt
concentrationMetrics-0.6.0.dist-info/RECORD
