Metadata-Version: 2.1
Name: concentrationMetrics
Version: 0.6.0
Summary: A python library for the computation of various concentration, inequality and diversity indices
Home-page: https://github.com/open-risk/concentrationMetrics
Author: Open Risk
Author-email: info@openrisk.eu
License: The MIT License (MIT)
Download-URL: https://github.com/open-risk/concentrationMetrics/archive/v_0.5.0.tar.gz
Keywords: concentration,diversity,inequality,index
Platform: UNKNOWN
Classifier: Intended Audience :: Developers
Classifier: Intended Audience :: Science/Research
Classifier: Intended Audience :: Financial and Insurance Industry
Classifier: Development Status :: 3 - Alpha
Classifier: License :: OSI Approved :: MIT License
Classifier: Operating System :: OS Independent
Classifier: Programming Language :: Python :: 3 :: Only
Classifier: Programming Language :: Python :: 3.6
Classifier: Topic :: Scientific/Engineering
Classifier: Topic :: Scientific/Engineering :: Information Analysis
Provides: concentrationMetrics
Requires-Dist: numpy
Requires-Dist: pandas
Requires-Dist: scipy
Requires-Dist: networkx
Requires-Dist: pytest
